Workbook

Sheet Summary
A1: Item | B1: Value | C1: Source
A2: Company | B2: Sandisk | C2: target config
A3: Ticker | B3: SNDK | C3: target config
A4: As of | B4: 2026-04-25 | C4: script argument
A5: Market cap | B5: 146110000000 | C5: data/valuation/valuation_snapshot.json
A6: Enterprise value | B6: 145380000000 | C6: data/valuation/valuation_snapshot.json
A7: Latest annual revenue | B7: 7355000000 | C7: data/statements/annual_statements.json
A8: Latest annual net income | B8: -1641000000 | C8: data/statements/annual_statements.json
A9: DCF implied enterprise value | B9: =DCF!B14 | C9: DCF sheet
A10: DCF implied equity value | B10: =DCF!B17 | C10: DCF sheet

Sheet Historical Statements
A1: period | B1: fiscal_year | C1: fiscal_period | D1: form | E1: filed | F1: revenue | G1: gross_profit | H1: operating_income | I1: net_income | J1: operating_cash_flow | K1: capital_expenditures | L1: cash | M1: debt | N1: assets | O1: liabilities | P1: stockholders_equity | Q1: shares_outstanding
A2: 2025 | B2: 2025 | C2: FY | D2: 10-K | E2: 2025-08-21 | F2: 7355000000 | G2: 2212000000 | H2: -1377000000 | I2: -1641000000 | J2: 84000000 | K2: -204000000 | L2: 1481000000 | M2: 1849000000 | N2: 12985000000 | O2: 3769000000 | P2: 9216000000 | Q2: 145000000

Sheet Operating Metrics
A1: period | B1: gross_margin | C1: operating_margin | D1: net_margin | E1: fcf_margin
A2: 2025 | B2: =IFERROR('Historical Statements'!G2/'Historical Statements'!F2,"") | C2: =IFERROR('Historical Statements'!H2/'Historical Statements'!F2,"") | D2: =IFERROR('Historical Statements'!I2/'Historical Statements'!F2,"") | E2: =IFERROR(('Historical Statements'!J2+'Historical Statements'!K2)/'Historical Statements'!F2,"")

Sheet Forecast
A1: metric | B1: latest | C1: Y1 | D1: Y2 | E1: Y3 | F1: Y4 | G1: Y5
A2: Revenue | B2: 7355000000 | C2: =B2*(1+Assumptions!B2) | D2: =C2*(1+Assumptions!B2) | E2: =D2*(1+Assumptions!B2) | F2: =E2*(1+Assumptions!B2) | G2: =F2*(1+Assumptions!B2)
A3: Operating Income | B3: -1377000000 | C3: =C2*Assumptions!B3 | D3: =D2*Assumptions!B3 | E3: =E2*Assumptions!B3 | F3: =F2*Assumptions!B3 | G3: =G2*Assumptions!B3
A4: NOPAT | C4: =C3*(1-Assumptions!B4) | D4: =D3*(1-Assumptions!B4) | E4: =E3*(1-Assumptions!B4) | F4: =F3*(1-Assumptions!B4) | G4: =G3*(1-Assumptions!B4)
A5: D&A | C5: =C2*Assumptions!B5 | D5: =D2*Assumptions!B5 | E5: =E2*Assumptions!B5 | F5: =F2*Assumptions!B5 | G5: =G2*Assumptions!B5
A6: Capex | B6: -204000000 | C6: =-C2*Assumptions!B6 | D6: =-D2*Assumptions!B6 | E6: =-E2*Assumptions!B6 | F6: =-F2*Assumptions!B6 | G6: =-G2*Assumptions!B6
A7: Change in NWC | C7: =-C2*Assumptions!B7 | D7: =-D2*Assumptions!B7 | E7: =-E2*Assumptions!B7 | F7: =-F2*Assumptions!B7 | G7: =-G2*Assumptions!B7
A8: Free Cash Flow | B8: -120000000 | C8: =SUM(C4:C7) | D8: =SUM(D4:D7) | E8: =SUM(E4:E7) | F8: =SUM(F4:F7) | G8: =SUM(G4:G7)

Sheet DCF
A1: Item | B1: Value
A2: WACC | B2: =Assumptions!B8
A3: Terminal growth | B3: =Assumptions!B9
A4: PV Y1 | B4: =IFERROR(Forecast!C8/(1+$B$2)^1,0)
A5: PV Y2 | B5: =IFERROR(Forecast!D8/(1+$B$2)^2,0)
A6: PV Y3 | B6: =IFERROR(Forecast!E8/(1+$B$2)^3,0)
A7: PV Y4 | B7: =IFERROR(Forecast!F8/(1+$B$2)^4,0)
A8: PV Y5 | B8: =IFERROR(Forecast!G8/(1+$B$2)^5,0)
A9: Terminal FCF | B9: =Forecast!G8*(1+$B$3)
A10: Terminal value | B10: =IFERROR(B9/($B$2-$B$3),0)
A11: PV terminal value | B11: =IFERROR(B10/(1+$B$2)^5,0)
A12: Enterprise value | B12: =SUM(B4:B8)+B11
A13: Cash | B13: 1481000000
A14: Debt | B14: 1849000000
A15: Equity value | B15: =B12+B13-B14
A16: Shares outstanding | B16: 145000000
A17: Implied price | B17: =IFERROR(B15/B16,"")

Sheet Comps
A1: ticker | B1: market_cap | C1: enterprise_value | D1: trailing_pe | E1: price_to_sales | F1: ev_to_ebitda | G1: source
A2: WDC | B2: 136970000000 | C2: 137730000000 | D2: 37.77 | E2: 12.76 | F2: 41.03 | G2: yahoo_chart_json + stockanalysis_statistics_page
A3: MU | B3: 560170000000 | C3: 554340000000 | D3: 23.37 | E3: 9.64 | F3: 15.06 | G3: yahoo_chart_json + stockanalysis_statistics_page
A4: STX | B4: 131330000000 | C4: 135090000000 | D4: 66.04 | E4: 13.06 | F4: 47.37 | G4: yahoo_chart_json + stockanalysis_statistics_page
A5: 285A.T | G5: yahoo_chart_json

Sheet Sensitivity
A1: Terminal growth \ WACC | B1: 0.08 | C1: 0.09 | D1: 0.1 | E1: 0.11 | F1: 0.12
A2: 0.01 | B2: =IFERROR((SUM(DCF!B4:B8)+(Forecast!G8*(1+0.01)/(0.08-0.01))/(1+0.08)^5)+DCF!B13-DCF!B14,"") | C2: =IFERROR((SUM(DCF!B4:B8)+(Forecast!G8*(1+0.01)/(0.09-0.01))/(1+0.09)^5)+DCF!B13-DCF!B14,"") | D2: =IFERROR((SUM(DCF!B4:B8)+(Forecast!G8*(1+0.01)/(0.1-0.01))/(1+0.1)^5)+DCF!B13-DCF!B14,"") | E2: =IFERROR((SUM(DCF!B4:B8)+(Forecast!G8*(1+0.01)/(0.11-0.01))/(1+0.11)^5)+DCF!B13-DCF!B14,"") | F2: =IFERROR((SUM(DCF!B4:B8)+(Forecast!G8*(1+0.01)/(0.12-0.01))/(1+0.12)^5)+DCF!B13-DCF!B14,"")
A3: 0.02 | B3: =IFERROR((SUM(DCF!B4:B8)+(Forecast!G8*(1+0.02)/(0.08-0.02))/(1+0.08)^5)+DCF!B13-DCF!B14,"") | C3: =IFERROR((SUM(DCF!B4:B8)+(Forecast!G8*(1+0.02)/(0.09-0.02))/(1+0.09)^5)+DCF!B13-DCF!B14,"") | D3: =IFERROR((SUM(DCF!B4:B8)+(Forecast!G8*(1+0.02)/(0.1-0.02))/(1+0.1)^5)+DCF!B13-DCF!B14,"") | E3: =IFERROR((SUM(DCF!B4:B8)+(Forecast!G8*(1+0.02)/(0.11-0.02))/(1+0.11)^5)+DCF!B13-DCF!B14,"") | F3: =IFERROR((SUM(DCF!B4:B8)+(Forecast!G8*(1+0.02)/(0.12-0.02))/(1+0.12)^5)+DCF!B13-DCF!B14,"")
A4: 0.03 | B4: =IFERROR((SUM(DCF!B4:B8)+(Forecast!G8*(1+0.03)/(0.08-0.03))/(1+0.08)^5)+DCF!B13-DCF!B14,"") | C4: =IFERROR((SUM(DCF!B4:B8)+(Forecast!G8*(1+0.03)/(0.09-0.03))/(1+0.09)^5)+DCF!B13-DCF!B14,"") | D4: =IFERROR((SUM(DCF!B4:B8)+(Forecast!G8*(1+0.03)/(0.1-0.03))/(1+0.1)^5)+DCF!B13-DCF!B14,"") | E4: =IFERROR((SUM(DCF!B4:B8)+(Forecast!G8*(1+0.03)/(0.11-0.03))/(1+0.11)^5)+DCF!B13-DCF!B14,"") | F4: =IFERROR((SUM(DCF!B4:B8)+(Forecast!G8*(1+0.03)/(0.12-0.03))/(1+0.12)^5)+DCF!B13-DCF!B14,"")
A5: 0.04 | B5: =IFERROR((SUM(DCF!B4:B8)+(Forecast!G8*(1+0.04)/(0.08-0.04))/(1+0.08)^5)+DCF!B13-DCF!B14,"") | C5: =IFERROR((SUM(DCF!B4:B8)+(Forecast!G8*(1+0.04)/(0.09-0.04))/(1+0.09)^5)+DCF!B13-DCF!B14,"") | D5: =IFERROR((SUM(DCF!B4:B8)+(Forecast!G8*(1+0.04)/(0.1-0.04))/(1+0.1)^5)+DCF!B13-DCF!B14,"") | E5: =IFERROR((SUM(DCF!B4:B8)+(Forecast!G8*(1+0.04)/(0.11-0.04))/(1+0.11)^5)+DCF!B13-DCF!B14,"") | F5: =IFERROR((SUM(DCF!B4:B8)+(Forecast!G8*(1+0.04)/(0.12-0.04))/(1+0.12)^5)+DCF!B13-DCF!B14,"")
A6: 0.05 | B6: =IFERROR((SUM(DCF!B4:B8)+(Forecast!G8*(1+0.05)/(0.08-0.05))/(1+0.08)^5)+DCF!B13-DCF!B14,"") | C6: =IFERROR((SUM(DCF!B4:B8)+(Forecast!G8*(1+0.05)/(0.09-0.05))/(1+0.09)^5)+DCF!B13-DCF!B14,"") | D6: =IFERROR((SUM(DCF!B4:B8)+(Forecast!G8*(1+0.05)/(0.1-0.05))/(1+0.1)^5)+DCF!B13-DCF!B14,"") | E6: =IFERROR((SUM(DCF!B4:B8)+(Forecast!G8*(1+0.05)/(0.11-0.05))/(1+0.11)^5)+DCF!B13-DCF!B14,"") | F6: =IFERROR((SUM(DCF!B4:B8)+(Forecast!G8*(1+0.05)/(0.12-0.05))/(1+0.12)^5)+DCF!B13-DCF!B14,"")

Sheet Capital Signals
A1: type | B1: name_or_form | C1: date | D1: value | E1: source
A2: insider_form | B2: 4 | C2: 2026-04-21 | D2: PRIMARY DOCUMENT | E2: data/capital_signals/insider_forms.json
A3: insider_form | B3: 4 | C3: 2026-04-21 | D3: PRIMARY DOCUMENT | E3: data/capital_signals/insider_forms.json
A4: insider_form | B4: 4 | C4: 2026-03-24 | D4: PRIMARY DOCUMENT | E4: data/capital_signals/insider_forms.json
A5: insider_form | B5: 4 | C5: 2026-03-05 | D5: PRIMARY DOCUMENT | E5: data/capital_signals/insider_forms.json
A6: insider_form | B6: 4 | C6: 2026-02-27 | D6: PRIMARY DOCUMENT | E6: data/capital_signals/insider_forms.json
A7: insider_form | B7: 4 | C7: 2026-02-27 | D7: PRIMARY DOCUMENT | E7: data/capital_signals/insider_forms.json
A8: insider_form | B8: 4 | C8: 2026-02-27 | D8: PRIMARY DOCUMENT | E8: data/capital_signals/insider_forms.json
A9: insider_form | B9: 4 | C9: 2026-02-26 | D9: PRIMARY DOCUMENT | E9: data/capital_signals/insider_forms.json
A10: insider_form | B10: 4 | C10: 2026-02-24 | D10: PRIMARY DOCUMENT | E10: data/capital_signals/insider_forms.json
A11: insider_form | B11: 4 | C11: 2026-02-24 | D11: PRIMARY DOCUMENT | E11: data/capital_signals/insider_forms.json
A12: insider_form | B12: 4 | C12: 2026-02-24 | D12: PRIMARY DOCUMENT | E12: data/capital_signals/insider_forms.json
... A93: insider_form | B93: 3 | C93: 2025-01-31 | D93: PRIMARY DOCUMENT | E93: data/capital_signals/insider_forms.json

Sheet Source Map
A1: metric | B1: source | C1: status
A2: revenue | B2: [{"tag": "RevenueFromContractWithCustomerExcludingAssessedTax", "form": "10-K", "fy": "2025", "fp": "FY", "filed": "2025-08-21", "end": "2025-06-27", "frame": "CY2024", "source": "sec_companyfacts.json", "selection_rule": "latest_period_with_quarter_duration_preference"}, {"tag": "RevenueFromContractWithCustomerExcludingAssessedTax", "form": "10-Q/A", "fy": "2025", "fp": "Q2", "filed": "2025-03-17", "end": "2023-12-29", "frame": "CY2023Q4", "source": "sec_companyfacts.json", "selection_rule": "l | C2: present
A3: gross_profit | B3: [{"tag": "GrossProfit", "form": "10-K", "fy": "2025", "fp": "FY", "filed": "2025-08-21", "end": "2025-06-27", "frame": "CY2024", "source": "sec_companyfacts.json", "selection_rule": "latest_period_with_quarter_duration_preference"}, {"tag": "GrossProfit", "form": "10-Q/A", "fy": "2025", "fp": "Q2", "filed": "2025-03-17", "end": "2023-12-29", "frame": "CY2023Q4", "source": "sec_companyfacts.json", "selection_rule": "latest_period_with_quarter_duration_preference"}, {"tag": "GrossProfit", "form": | C3: present
A4: operating_income | B4: [{"tag": "OperatingIncomeLoss", "form": "10-K", "fy": "2025", "fp": "FY", "filed": "2025-08-21", "end": "2025-06-27", "frame": "CY2024", "source": "sec_companyfacts.json", "selection_rule": "latest_period_with_quarter_duration_preference"}, {"tag": "OperatingIncomeLoss", "form": "10-Q/A", "fy": "2025", "fp": "Q2", "filed": "2025-03-17", "end": "2023-12-29", "frame": "CY2023Q4", "source": "sec_companyfacts.json", "selection_rule": "latest_period_with_quarter_duration_preference"}, {"tag": "Operat | C4: present
A5: net_income | B5: [{"tag": "NetIncomeLoss", "form": "10-K", "fy": "2025", "fp": "FY", "filed": "2025-08-21", "end": "2025-06-27", "frame": "CY2024", "source": "sec_companyfacts.json", "selection_rule": "latest_period_with_quarter_duration_preference"}, {"tag": "NetIncomeLoss", "form": "10-Q/A", "fy": "2025", "fp": "Q2", "filed": "2025-03-17", "end": "2024-12-27", "frame": null, "source": "sec_companyfacts.json", "selection_rule": "latest_period_with_quarter_duration_preference"}, {"tag": "NetIncomeLoss", "form": | C5: present
A6: operating_cash_flow | B6: [{"tag": "NetCashProvidedByUsedInOperatingActivities", "form": "10-K", "fy": "2025", "fp": "FY", "filed": "2025-08-21", "end": "2025-06-27", "frame": "CY2024", "source": "sec_companyfacts.json", "selection_rule": "latest_period_with_quarter_duration_preference"}, {"tag": "NetCashProvidedByUsedInOperatingActivities", "form": "10-Q/A", "fy": "2025", "fp": "Q2", "filed": "2025-03-17", "end": "2024-12-27", "frame": null, "source": "sec_companyfacts.json", "selection_rule": "latest_period_with_quarte | C6: present
A7: capital_expenditures | B7: [{"tag": "PaymentsToAcquirePropertyPlantAndEquipment", "form": "10-K", "fy": "2025", "fp": "FY", "filed": "2025-08-21", "end": "2025-06-27", "frame": "CY2024", "source": "sec_companyfacts.json", "selection_rule": "latest_period_with_quarter_duration_preference"}, {"tag": "PaymentsToAcquirePropertyPlantAndEquipment", "form": "10-Q/A", "fy": "2025", "fp": "Q2", "filed": "2025-03-17", "end": "2024-12-27", "frame": null, "source": "sec_companyfacts.json", "selection_rule": "latest_period_with_quarte | C7: present
A8: cash | B8: [{"tag": "CashAndCashEquivalentsAtCarryingValue", "form": "10-Q/A", "fy": "2025", "fp": "Q2", "filed": "2025-03-17", "end": "2024-12-27", "frame": "CY2024Q4I", "source": "sec_companyfacts.json", "selection_rule": "latest_period_with_quarter_duration_preference"}, {"tag": "CashAndCashEquivalentsAtCarryingValue", "form": "10-Q", "fy": "2025", "fp": "Q3", "filed": "2025-05-12", "end": "2025-03-28", "frame": "CY2025Q1I", "source": "sec_companyfacts.json", "selection_rule": "latest_period_with_quarte | C8: present
A9: debt | B9: "data/statements/annual_statements.json" | C9: present
A10: assets | B10: [{"tag": "Assets", "form": "10-Q/A", "fy": "2025", "fp": "Q2", "filed": "2025-03-17", "end": "2024-12-27", "frame": "CY2024Q4I", "source": "sec_companyfacts.json", "selection_rule": "latest_period_with_quarter_duration_preference"}, {"tag": "Assets", "form": "10-Q", "fy": "2025", "fp": "Q3", "filed": "2025-05-12", "end": "2025-03-28", "frame": "CY2025Q1I", "source": "sec_companyfacts.json", "selection_rule": "latest_period_with_quarter_duration_preference"}, {"tag": "Assets", "form": "10-K", "fy | C10: present
A11: liabilities | B11: [{"tag": "Liabilities", "form": "10-Q/A", "fy": "2025", "fp": "Q2", "filed": "2025-03-17", "end": "2024-12-27", "frame": "CY2024Q4I", "source": "sec_companyfacts.json", "selection_rule": "latest_period_with_quarter_duration_preference"}, {"tag": "Liabilities", "form": "10-Q", "fy": "2025", "fp": "Q3", "filed": "2025-05-12", "end": "2025-03-28", "frame": "CY2025Q1I", "source": "sec_companyfacts.json", "selection_rule": "latest_period_with_quarter_duration_preference"}, {"tag": "Liabilities", "for | C11: present
A12: stockholders_equity | B12: [{"tag": "StockholdersEquity", "form": "10-K", "fy": "2025", "fp": "FY", "filed": "2025-08-21", "end": "2025-06-27", "frame": null, "source": "sec_companyfacts.json", "selection_rule": "latest_period_with_quarter_duration_preference"}, {"tag": "StockholdersEquity", "form": "10-Q/A", "fy": "2025", "fp": "Q2", "filed": "2025-03-17", "end": "2024-12-27", "frame": null, "source": "sec_companyfacts.json", "selection_rule": "latest_period_with_quarter_duration_preference"}, {"tag": "StockholdersEquity | C12: present
... A15: valuation | B15: data/valuation/valuation_snapshot.json | C15: present

Sheet Assumptions
A1: name | B1: value | C1: status | D1: description
A2: revenue_growth | B2: 0.05 | C2: auto_default | D2: Base forecast revenue growth
A3: operating_margin | B3: 0.12 | C3: auto_default | D3: Base forecast operating margin
A4: tax_rate | B4: 0.21 | C4: auto_default | D4: Cash tax rate
A5: da_percent_revenue | B5: 0.04 | C5: auto_default | D5: D&A as % of revenue
A6: capex_percent_revenue | B6: 0.08 | C6: auto_default | D6: Capital expenditure as % of revenue
A7: nwc_percent_revenue | B7: 0.02 | C7: auto_default | D7: Change in working capital as % of revenue
A8: wacc | B8: 0.1 | C8: auto_default | D8: Weighted average cost of capital
A9: terminal_growth | B9: 0.03 | C9: auto_default | D9: Terminal growth rate
