Workbook

Sheet Summary
A1: Item | B1: Value | C1: Source
A2: Company | B2: Sandisk | C2: target config
A3: Ticker | B3: SNDK | C3: target config
A4: As of | B4: 2026-04-26 | C4: script argument
A5: Market cap | B5: 146110000000 | C5: data/valuation/valuation_snapshot.json
A6: Enterprise value | B6: 145380000000 | C6: data/valuation/valuation_snapshot.json
A7: Latest annual revenue | B7: ='Historical Statements'!F4 -> 7355000000 | C7: data/statements/annual_statements.json
A8: Latest annual net income | B8: ='Historical Statements'!I4 -> -1641000000 | C8: data/statements/annual_statements.json
A9: DCF implied enterprise value | B9: =DCF!B12 -> 4.100065e+09 | C9: DCF sheet
A10: DCF implied equity value | B10: =DCF!B15 -> 3.732065e+09 | C10: DCF sheet
A11: DCF implied price | B11: =DCF!B17 -> 25.738379 | C11: DCF sheet

Sheet Historical Statements
A1: period | B1: fiscal_year | C1: fiscal_period | D1: form | E1: filed | F1: revenue | G1: gross_profit | H1: operating_income | I1: net_income | J1: operating_cash_flow | K1: capital_expenditures | L1: cash | M1: debt | N1: assets | O1: liabilities | P1: stockholders_equity | Q1: shares_outstanding
A2: 2023 | B2: 2023 | C2: FY | D2: 10-K | E2: 2025-08-21 | F2: 6086000000 | G2: 430000000 | H2: -2035000000 | I2: -2143000000 | J2: -713000000 | K2: -219000000 | L2: 292000000 | P2: 11439000000 | Q2: 145000000
A3: 2024 | B3: 2024 | C3: FY | D3: 10-K | E3: 2025-08-21 | F3: 6663000000 | G3: 1072000000 | H3: -468000000 | I3: -672000000 | J3: -309000000 | K3: -166000000 | L3: 328000000 | N3: 13506000000 | O3: 2424000000 | P3: 11082000000 | Q3: 145000000
A4: 2025 | B4: 2025 | C4: FY | D4: 10-K | E4: 2025-08-21 | F4: 7355000000 | G4: 2212000000 | H4: -1377000000 | I4: -1641000000 | J4: 84000000 | K4: -204000000 | L4: 1481000000 | M4: 1849000000 | N4: 12985000000 | O4: 3769000000 | P4: 9216000000 | Q4: 145000000

Sheet Operating Metrics
A1: period | B1: gross_margin | C1: operating_margin | D1: net_margin | E1: fcf_margin
A2: 2023 | B2: =IFERROR('Historical Statements'!G2/'Historical Statements'!F2,"") -> 0.07065396 | C2: =IFERROR('Historical Statements'!H2/'Historical Statements'!F2,"") -> -0.33437397 | D2: =IFERROR('Historical Statements'!I2/'Historical Statements'!F2,"") -> -0.35211962 | E2: =IFERROR(('Historical Statements'!J2+'Historical Statements'!K2)/'Historical Statements'!F2,"") -> -0.15313835
A3: 2024 | B3: =IFERROR('Historical Statements'!G3/'Historical Statements'!F3,"") -> 0.16088849 | C3: =IFERROR('Historical Statements'!H3/'Historical Statements'!F3,"") -> -0.070238631 | D3: =IFERROR('Historical Statements'!I3/'Historical Statements'!F3,"") -> -0.10085547 | E3: =IFERROR(('Historical Statements'!J3+'Historical Statements'!K3)/'Historical Statements'!F3,"") -> -0.071289209
A4: 2025 | B4: =IFERROR('Historical Statements'!G4/'Historical Statements'!F4,"") -> 0.30074779 | C4: =IFERROR('Historical Statements'!H4/'Historical Statements'!F4,"") -> -0.18721958 | D4: =IFERROR('Historical Statements'!I4/'Historical Statements'!F4,"") -> -0.22311353 | E4: =IFERROR(('Historical Statements'!J4+'Historical Statements'!K4)/'Historical Statements'!F4,"") -> -0.016315432

Sheet Forecast
A1: metric | B1: latest | C1: Y1 | D1: Y2 | E1: Y3 | F1: Y4 | G1: Y5
A2: Revenue | B2: ='Historical Statements'!F4 -> 7355000000 | C2: =B2*(1+Assumptions!$B$2) -> 7722750000 | D2: =C2*(1+Assumptions!$B$2) -> 8108887500 | E2: =D2*(1+Assumptions!$B$2) -> 8514331875 | F2: =E2*(1+Assumptions!$B$2) -> 8.9400485e+09 | G2: =F2*(1+Assumptions!$B$2) -> 9.3870509e+09
A3: Operating Income | B3: ='Historical Statements'!H4 -> -1377000000 | C3: =C2*Assumptions!$B$3 -> 926730000 | D3: =D2*Assumptions!$B$3 -> 973066500 | E3: =E2*Assumptions!$B$3 -> 1021719825 | F3: =F2*Assumptions!$B$3 -> 1.0728058e+09 | G3: =G2*Assumptions!$B$3 -> 1.1264461e+09
A4: NOPAT | C4: =C3*(1-Assumptions!$B$4) -> 732116700 | D4: =D3*(1-Assumptions!$B$4) -> 768722535 | E4: =E3*(1-Assumptions!$B$4) -> 8.0715866e+08 | F4: =F3*(1-Assumptions!$B$4) -> 8.4751659e+08 | G4: =G3*(1-Assumptions!$B$4) -> 8.8989242e+08
A5: D&A | C5: =C2*Assumptions!$B$5 -> 308910000 | D5: =D2*Assumptions!$B$5 -> 324355500 | E5: =E2*Assumptions!$B$5 -> 340573275 | F5: =F2*Assumptions!$B$5 -> 3.5760194e+08 | G5: =G2*Assumptions!$B$5 -> 3.7548204e+08
A6: Capex | B6: ='Historical Statements'!K4 -> -204000000 | C6: =-C2*Assumptions!$B$6 -> -617820000 | D6: =-D2*Assumptions!$B$6 -> -648711000 | E6: =-E2*Assumptions!$B$6 -> -681146550 | F6: =-F2*Assumptions!$B$6 -> -7.1520388e+08 | G6: =-G2*Assumptions!$B$6 -> -7.5096407e+08
A7: Change in NWC | C7: =-C2*Assumptions!$B$7 -> -154455000 | D7: =-D2*Assumptions!$B$7 -> -162177750 | E7: =-E2*Assumptions!$B$7 -> -1.7028664e+08 | F7: =-F2*Assumptions!$B$7 -> -1.7880097e+08 | G7: =-G2*Assumptions!$B$7 -> -1.8774102e+08
A8: Free Cash Flow | B8: ='Historical Statements'!J4+'Historical Statements'!K4 -> -120000000 | C8: =C4+C5+C6+C7 -> 268751700 | D8: =D4+D5+D6+D7 -> 282189285 | E8: =E4+E5+E6+E7 -> 2.9629875e+08 | F8: =F4+F5+F6+F7 -> 3.1111369e+08 | G8: =G4+G5+G6+G7 -> 3.2666937e+08

Sheet DCF
A1: Item | B1: Value
A2: WACC | B2: =Assumptions!$B$8 -> 0.1
A3: Terminal growth | B3: =Assumptions!$B$9 -> 0.03
A4: PV Y1 | B4: =Forecast!C8/(1+$B$2)^1 -> 2.4431973e+08
A5: PV Y2 | B5: =Forecast!D8/(1+$B$2)^2 -> 2.3321429e+08
A6: PV Y3 | B6: =Forecast!E8/(1+$B$2)^3 -> 2.2261364e+08
A7: PV Y4 | B7: =Forecast!F8/(1+$B$2)^4 -> 2.1249483e+08
A8: PV Y5 | B8: =Forecast!G8/(1+$B$2)^5 -> 2.0283598e+08
A9: Terminal FCF | B9: =Forecast!G8*(1+$B$3) -> 3.3646945e+08
A10: Terminal value | B10: =$B$9/($B$2-$B$3) -> 4.8067065e+09
A11: PV terminal value | B11: =$B$10/(1+$B$2)^5 -> 2.9845865e+09
A12: Enterprise value | B12: =SUM($B$4:$B$8)+$B$11 -> 4.100065e+09
A13: Cash | B13: ='Historical Statements'!L4 -> 1481000000
A14: Debt | B14: ='Historical Statements'!M4 -> 1849000000
A15: Equity value | B15: =$B$12+$B$13-$B$14 -> 3.732065e+09
A16: Shares outstanding | B16: ='Historical Statements'!Q4 -> 145000000
A17: Implied price | B17: =IFERROR($B$15/$B$16,"") -> 25.738379

Sheet Comps
A1: ticker | B1: market_cap | C1: enterprise_value | D1: trailing_pe | E1: price_to_sales | F1: ev_to_ebitda | G1: source
A2: WDC | B2: 136970000000 | C2: 137730000000 | D2: 37.77 | E2: 12.76 | F2: 41.03 | G2: yahoo_chart_json + stockanalysis_statistics_page
A3: MU | B3: 560170000000 | C3: 554340000000 | D3: 23.37 | E3: 9.64 | F3: 15.06 | G3: yahoo_chart_json + stockanalysis_statistics_page
A4: STX | B4: 131330000000 | C4: 135090000000 | D4: 66.04 | E4: 13.06 | F4: 47.37 | G4: yahoo_chart_json + stockanalysis_statistics_page
A5: 285A.T | G5: yahoo_chart_json

Sheet Sensitivity
A1: Terminal growth \ WACC | B1: 0.08 | C1: 0.09 | D1: 0.1 | E1: 0.11 | F1: 0.12
A2: 0.01 | B2: =IF(B$1>$A2,SUM(Forecast!C8/(1+B$1)^1,Forecast!D8/(1+B$1)^2,Forecast!E8/(1+B$1)^3,Forecast!F8/(1+B$1)^4,Forecast!G8/(1+B$1)^5)+Forecast!G8*(1+$A2)/(B$1-$A2)/(1+B$1)^5+DCF!$B$13-DCF!$B$14,"") -> 4.0168331e+09 | C2: =IF(C$1>$A2,SUM(Forecast!C8/(1+C$1)^1,Forecast!D8/(1+C$1)^2,Forecast!E8/(1+C$1)^3,Forecast!F8/(1+C$1)^4,Forecast!G8/(1+C$1)^5)+Forecast!G8*(1+$A2)/(C$1-$A2)/(1+C$1)^5+DCF!$B$13-DCF!$B$14,"") -> 3.4580323e+09 | D2: =IF(D$1>$A2,SUM(Forecast!C8/(1+D$1)^1,Forecast!D8/(1+D$1)^2,Forecast!E8/(1+D$1)^3,Forecast!F8/(1+D$1)^4,Forecast!G8/(1+D$1)^5)+Forecast!G8*(1+$A2)/(D$1-$A2)/(1+D$1)^5+DCF!$B$13-DCF!$B$14,"") -> 3.0237489e+09 | E2: =IF(E$1>$A2,SUM(Forecast!C8/(1+E$1)^1,Forecast!D8/(1+E$1)^2,Forecast!E8/(1+E$1)^3,Forecast!F8/(1+E$1)^4,Forecast!G8/(1+E$1)^5)+Forecast!G8*(1+$A2)/(E$1-$A2)/(1+E$1)^5+DCF!$B$13-DCF!$B$14,"") -> 2.6766134e+09 | F2: =IF(F$1>$A2,SUM(Forecast!C8/(1+F$1)^1,Forecast!D8/(1+F$1)^2,Forecast!E8/(1+F$1)^3,Forecast!F8/(1+F$1)^4,Forecast!G8/(1+F$1)^5)+Forecast!G8*(1+$A2)/(F$1-$A2)/(1+F$1)^5+DCF!$B$13-DCF!$B$14,"") -> 2.3928462e+09
A3: 0.02 | B3: =IF(B$1>$A3,SUM(Forecast!C8/(1+B$1)^1,Forecast!D8/(1+B$1)^2,Forecast!E8/(1+B$1)^3,Forecast!F8/(1+B$1)^4,Forecast!G8/(1+B$1)^5)+Forecast!G8*(1+$A3)/(B$1-$A3)/(1+B$1)^5+DCF!$B$13-DCF!$B$14,"") -> 4.5885277e+09 | C3: =IF(C$1>$A3,SUM(Forecast!C8/(1+C$1)^1,Forecast!D8/(1+C$1)^2,Forecast!E8/(1+C$1)^3,Forecast!F8/(1+C$1)^4,Forecast!G8/(1+C$1)^5)+Forecast!G8*(1+$A3)/(C$1-$A3)/(1+C$1)^5+DCF!$B$13-DCF!$B$14,"") -> 3.8712837e+09 | D3: =IF(D$1>$A3,SUM(Forecast!C8/(1+D$1)^1,Forecast!D8/(1+D$1)^2,Forecast!E8/(1+D$1)^3,Forecast!F8/(1+D$1)^4,Forecast!G8/(1+D$1)^5)+Forecast!G8*(1+$A3)/(D$1-$A3)/(1+D$1)^5+DCF!$B$13-DCF!$B$14,"") -> 3.3336372e+09 | E3: =IF(E$1>$A3,SUM(Forecast!C8/(1+E$1)^1,Forecast!D8/(1+E$1)^2,Forecast!E8/(1+E$1)^3,Forecast!F8/(1+E$1)^4,Forecast!G8/(1+E$1)^5)+Forecast!G8*(1+$A3)/(E$1-$A3)/(1+E$1)^5+DCF!$B$13-DCF!$B$14,"") -> 2.9157104e+09 | F3: =IF(F$1>$A3,SUM(Forecast!C8/(1+F$1)^1,Forecast!D8/(1+F$1)^2,Forecast!E8/(1+F$1)^3,Forecast!F8/(1+F$1)^4,Forecast!G8/(1+F$1)^5)+Forecast!G8*(1+$A3)/(F$1-$A3)/(1+F$1)^5+DCF!$B$13-DCF!$B$14,"") -> 2.5815773e+09
A4: 0.03 | B4: =IF(B$1>$A4,SUM(Forecast!C8/(1+B$1)^1,Forecast!D8/(1+B$1)^2,Forecast!E8/(1+B$1)^3,Forecast!F8/(1+B$1)^4,Forecast!G8/(1+B$1)^5)+Forecast!G8*(1+$A4)/(B$1-$A4)/(1+B$1)^5+DCF!$B$13-DCF!$B$14,"") -> 5.3889001e+09 | C4: =IF(C$1>$A4,SUM(Forecast!C8/(1+C$1)^1,Forecast!D8/(1+C$1)^2,Forecast!E8/(1+C$1)^3,Forecast!F8/(1+C$1)^4,Forecast!G8/(1+C$1)^5)+Forecast!G8*(1+$A4)/(C$1-$A4)/(1+C$1)^5+DCF!$B$13-DCF!$B$14,"") -> 4.4222857e+09 | D4: =IF(D$1>$A4,SUM(Forecast!C8/(1+D$1)^1,Forecast!D8/(1+D$1)^2,Forecast!E8/(1+D$1)^3,Forecast!F8/(1+D$1)^4,Forecast!G8/(1+D$1)^5)+Forecast!G8*(1+$A4)/(D$1-$A4)/(1+D$1)^5+DCF!$B$13-DCF!$B$14,"") -> 3.732065e+09 | E4: =IF(E$1>$A4,SUM(Forecast!C8/(1+E$1)^1,Forecast!D8/(1+E$1)^2,Forecast!E8/(1+E$1)^3,Forecast!F8/(1+E$1)^4,Forecast!G8/(1+E$1)^5)+Forecast!G8*(1+$A4)/(E$1-$A4)/(1+E$1)^5+DCF!$B$13-DCF!$B$14,"") -> 3.2145815e+09 | F4: =IF(F$1>$A4,SUM(Forecast!C8/(1+F$1)^1,Forecast!D8/(1+F$1)^2,Forecast!E8/(1+F$1)^3,Forecast!F8/(1+F$1)^4,Forecast!G8/(1+F$1)^5)+Forecast!G8*(1+$A4)/(F$1-$A4)/(1+F$1)^5+DCF!$B$13-DCF!$B$14,"") -> 2.8122488e+09
A5: 0.04 | B5: =IF(B$1>$A5,SUM(Forecast!C8/(1+B$1)^1,Forecast!D8/(1+B$1)^2,Forecast!E8/(1+B$1)^3,Forecast!F8/(1+B$1)^4,Forecast!G8/(1+B$1)^5)+Forecast!G8*(1+$A5)/(B$1-$A5)/(1+B$1)^5+DCF!$B$13-DCF!$B$14,"") -> 6.5894588e+09 | C5: =IF(C$1>$A5,SUM(Forecast!C8/(1+C$1)^1,Forecast!D8/(1+C$1)^2,Forecast!E8/(1+C$1)^3,Forecast!F8/(1+C$1)^4,Forecast!G8/(1+C$1)^5)+Forecast!G8*(1+$A5)/(C$1-$A5)/(1+C$1)^5+DCF!$B$13-DCF!$B$14,"") -> 5.1936884e+09 | D5: =IF(D$1>$A5,SUM(Forecast!C8/(1+D$1)^1,Forecast!D8/(1+D$1)^2,Forecast!E8/(1+D$1)^3,Forecast!F8/(1+D$1)^4,Forecast!G8/(1+D$1)^5)+Forecast!G8*(1+$A5)/(D$1-$A5)/(1+D$1)^5+DCF!$B$13-DCF!$B$14,"") -> 4.2633021e+09 | E5: =IF(E$1>$A5,SUM(Forecast!C8/(1+E$1)^1,Forecast!D8/(1+E$1)^2,Forecast!E8/(1+E$1)^3,Forecast!F8/(1+E$1)^4,Forecast!G8/(1+E$1)^5)+Forecast!G8*(1+$A5)/(E$1-$A5)/(1+E$1)^5+DCF!$B$13-DCF!$B$14,"") -> 3.5988444e+09 | F5: =IF(F$1>$A5,SUM(Forecast!C8/(1+F$1)^1,Forecast!D8/(1+F$1)^2,Forecast!E8/(1+F$1)^3,Forecast!F8/(1+F$1)^4,Forecast!G8/(1+F$1)^5)+Forecast!G8*(1+$A5)/(F$1-$A5)/(1+F$1)^5+DCF!$B$13-DCF!$B$14,"") -> 3.1005881e+09
A6: 0.05 | B6: =IF(B$1>$A6,SUM(Forecast!C8/(1+B$1)^1,Forecast!D8/(1+B$1)^2,Forecast!E8/(1+B$1)^3,Forecast!F8/(1+B$1)^4,Forecast!G8/(1+B$1)^5)+Forecast!G8*(1+$A6)/(B$1-$A6)/(1+B$1)^5+DCF!$B$13-DCF!$B$14,"") -> 8.59039e+09 | C6: =IF(C$1>$A6,SUM(Forecast!C8/(1+C$1)^1,Forecast!D8/(1+C$1)^2,Forecast!E8/(1+C$1)^3,Forecast!F8/(1+C$1)^4,Forecast!G8/(1+C$1)^5)+Forecast!G8*(1+$A6)/(C$1-$A6)/(1+C$1)^5+DCF!$B$13-DCF!$B$14,"") -> 6350792500 | D6: =IF(D$1>$A6,SUM(Forecast!C8/(1+D$1)^1,Forecast!D8/(1+D$1)^2,Forecast!E8/(1+D$1)^3,Forecast!F8/(1+D$1)^4,Forecast!G8/(1+D$1)^5)+Forecast!G8*(1+$A6)/(D$1-$A6)/(1+D$1)^5+DCF!$B$13-DCF!$B$14,"") -> 5.007034e+09 | E6: =IF(E$1>$A6,SUM(Forecast!C8/(1+E$1)^1,Forecast!D8/(1+E$1)^2,Forecast!E8/(1+E$1)^3,Forecast!F8/(1+E$1)^4,Forecast!G8/(1+E$1)^5)+Forecast!G8*(1+$A6)/(E$1-$A6)/(1+E$1)^5+DCF!$B$13-DCF!$B$14,"") -> 4.111195e+09 | F6: =IF(F$1>$A6,SUM(Forecast!C8/(1+F$1)^1,Forecast!D8/(1+F$1)^2,Forecast!E8/(1+F$1)^3,Forecast!F8/(1+F$1)^4,Forecast!G8/(1+F$1)^5)+Forecast!G8*(1+$A6)/(F$1-$A6)/(1+F$1)^5+DCF!$B$13-DCF!$B$14,"") -> 3.47131e+09

Sheet Capital Signals
A1: type | B1: name_or_form | C1: date | D1: value | E1: source
A2: insider_form | B2: 4 | C2: 2026-04-21 | D2: PRIMARY DOCUMENT | E2: data/capital_signals/insider_forms.json
A3: insider_form | B3: 4 | C3: 2026-04-21 | D3: PRIMARY DOCUMENT | E3: data/capital_signals/insider_forms.json
A4: insider_form | B4: 4 | C4: 2026-03-24 | D4: PRIMARY DOCUMENT | E4: data/capital_signals/insider_forms.json
A5: insider_form | B5: 4 | C5: 2026-03-05 | D5: PRIMARY DOCUMENT | E5: data/capital_signals/insider_forms.json
A6: insider_form | B6: 4 | C6: 2026-02-27 | D6: PRIMARY DOCUMENT | E6: data/capital_signals/insider_forms.json
A7: insider_form | B7: 4 | C7: 2026-02-27 | D7: PRIMARY DOCUMENT | E7: data/capital_signals/insider_forms.json
A8: insider_form | B8: 4 | C8: 2026-02-27 | D8: PRIMARY DOCUMENT | E8: data/capital_signals/insider_forms.json
A9: insider_form | B9: 4 | C9: 2026-02-26 | D9: PRIMARY DOCUMENT | E9: data/capital_signals/insider_forms.json
A10: insider_form | B10: 4 | C10: 2026-02-24 | D10: PRIMARY DOCUMENT | E10: data/capital_signals/insider_forms.json
A11: insider_form | B11: 4 | C11: 2026-02-24 | D11: PRIMARY DOCUMENT | E11: data/capital_signals/insider_forms.json
A12: insider_form | B12: 4 | C12: 2026-02-24 | D12: PRIMARY DOCUMENT | E12: data/capital_signals/insider_forms.json
... A118: institutional_holder | B118: Dimensional Fund Advisors Lp | C118: 12/31/2025 | D118: 958,462 | E118: data/capital_signals/institutional_holders.json

Sheet Source Map
A1: metric | B1: source | C1: status
A2: revenue | B2: [{"tag": "RevenueFromContractWithCustomerExcludingAssessedTax", "form": "10-K", "fy": "2025", "fp": "FY", "period": "2023", "filed": "2025-08-21", "end": "2023-06-30", "frame": null, "source": "sec_companyfacts.json", "selection_rule": "annual_by_actual_end_year_or_quarter_duration_preference"}, {"tag": "RevenueFromContractWithCustomerExcludingAssessedTax", "form": "10-Q/A", "fy": "2025", "fp": "Q2", "period": "2025-Q2", "filed": "2025-03-17", "end": "2023-12-29", "frame": "CY2023Q4", "source": | C2: present
A3: gross_profit | B3: [{"tag": "GrossProfit", "form": "10-K", "fy": "2025", "fp": "FY", "period": "2023", "filed": "2025-08-21", "end": "2023-06-30", "frame": null, "source": "sec_companyfacts.json", "selection_rule": "annual_by_actual_end_year_or_quarter_duration_preference"}, {"tag": "GrossProfit", "form": "10-Q/A", "fy": "2025", "fp": "Q2", "period": "2025-Q2", "filed": "2025-03-17", "end": "2023-12-29", "frame": "CY2023Q4", "source": "sec_companyfacts.json", "selection_rule": "annual_by_actual_end_year_or_quarter | C3: present
A4: operating_income | B4: [{"tag": "OperatingIncomeLoss", "form": "10-K", "fy": "2025", "fp": "FY", "period": "2023", "filed": "2025-08-21", "end": "2023-06-30", "frame": null, "source": "sec_companyfacts.json", "selection_rule": "annual_by_actual_end_year_or_quarter_duration_preference"}, {"tag": "OperatingIncomeLoss", "form": "10-Q/A", "fy": "2025", "fp": "Q2", "period": "2025-Q2", "filed": "2025-03-17", "end": "2023-12-29", "frame": "CY2023Q4", "source": "sec_companyfacts.json", "selection_rule": "annual_by_actual_end | C4: present
A5: net_income | B5: [{"tag": "NetIncomeLoss", "form": "10-K", "fy": "2025", "fp": "FY", "period": "2023", "filed": "2025-08-21", "end": "2023-06-30", "frame": null, "source": "sec_companyfacts.json", "selection_rule": "annual_by_actual_end_year_or_quarter_duration_preference"}, {"tag": "NetIncomeLoss", "form": "10-Q/A", "fy": "2025", "fp": "Q2", "period": "2025-Q2", "filed": "2025-03-17", "end": "2024-12-27", "frame": null, "source": "sec_companyfacts.json", "selection_rule": "annual_by_actual_end_year_or_quarter_d | C5: present
A6: operating_cash_flow | B6: [{"tag": "NetCashProvidedByUsedInOperatingActivities", "form": "10-K", "fy": "2025", "fp": "FY", "period": "2023", "filed": "2025-08-21", "end": "2023-06-30", "frame": null, "source": "sec_companyfacts.json", "selection_rule": "annual_by_actual_end_year_or_quarter_duration_preference"}, {"tag": "NetCashProvidedByUsedInOperatingActivities", "form": "10-Q/A", "fy": "2025", "fp": "Q2", "period": "2025-Q2", "filed": "2025-03-17", "end": "2024-12-27", "frame": null, "source": "sec_companyfacts.json", | C6: present
A7: capital_expenditures | B7: [{"tag": "PaymentsToAcquirePropertyPlantAndEquipment", "form": "10-K", "fy": "2025", "fp": "FY", "period": "2023", "filed": "2025-08-21", "end": "2023-06-30", "frame": null, "source": "sec_companyfacts.json", "selection_rule": "annual_by_actual_end_year_or_quarter_duration_preference"}, {"tag": "PaymentsToAcquirePropertyPlantAndEquipment", "form": "10-Q/A", "fy": "2025", "fp": "Q2", "period": "2025-Q2", "filed": "2025-03-17", "end": "2024-12-27", "frame": null, "source": "sec_companyfacts.json", | C7: present
A8: cash | B8: [{"tag": "CashAndCashEquivalentsAtCarryingValue", "form": "10-Q/A", "fy": "2025", "fp": "Q2", "period": "2025-Q2", "filed": "2025-03-17", "end": "2024-12-27", "frame": "CY2024Q4I", "source": "sec_companyfacts.json", "selection_rule": "annual_by_actual_end_year_or_quarter_duration_preference"}, {"tag": "CashAndCashEquivalentsAtCarryingValue", "form": "10-Q", "fy": "2025", "fp": "Q3", "period": "2025-Q3", "filed": "2025-05-12", "end": "2025-03-28", "frame": "CY2025Q1I", "source": "sec_companyfacts | C8: present
A9: debt | B9: "data/statements/annual_statements.json" | C9: present
A10: assets | B10: [{"tag": "Assets", "form": "10-Q/A", "fy": "2025", "fp": "Q2", "period": "2025-Q2", "filed": "2025-03-17", "end": "2024-12-27", "frame": "CY2024Q4I", "source": "sec_companyfacts.json", "selection_rule": "annual_by_actual_end_year_or_quarter_duration_preference"}, {"tag": "Assets", "form": "10-Q", "fy": "2025", "fp": "Q3", "period": "2025-Q3", "filed": "2025-05-12", "end": "2025-03-28", "frame": "CY2025Q1I", "source": "sec_companyfacts.json", "selection_rule": "annual_by_actual_end_year_or_quarte | C10: present
A11: liabilities | B11: [{"tag": "Liabilities", "form": "10-Q/A", "fy": "2025", "fp": "Q2", "period": "2025-Q2", "filed": "2025-03-17", "end": "2024-12-27", "frame": "CY2024Q4I", "source": "sec_companyfacts.json", "selection_rule": "annual_by_actual_end_year_or_quarter_duration_preference"}, {"tag": "Liabilities", "form": "10-Q", "fy": "2025", "fp": "Q3", "period": "2025-Q3", "filed": "2025-05-12", "end": "2025-03-28", "frame": "CY2025Q1I", "source": "sec_companyfacts.json", "selection_rule": "annual_by_actual_end_year | C11: present
A12: stockholders_equity | B12: [{"tag": "StockholdersEquity", "form": "10-K", "fy": "2025", "fp": "FY", "period": "2022", "filed": "2025-08-21", "end": "2022-07-01", "frame": "CY2022Q2I", "source": "sec_companyfacts.json", "selection_rule": "annual_by_actual_end_year_or_quarter_duration_preference"}, {"tag": "StockholdersEquity", "form": "10-Q/A", "fy": "2025", "fp": "Q2", "period": "2025-Q2", "filed": "2025-03-17", "end": "2024-12-27", "frame": null, "source": "sec_companyfacts.json", "selection_rule": "annual_by_actual_end_ | C12: present
... A15: valuation | B15: data/valuation/valuation_snapshot.json | C15: present

Sheet Assumptions
A1: name | B1: value | C1: status | D1: description
A2: revenue_growth | B2: 0.05 | C2: auto_default | D2: Base forecast revenue growth
A3: operating_margin | B3: 0.12 | C3: auto_default | D3: Base forecast operating margin
A4: tax_rate | B4: 0.21 | C4: auto_default | D4: Cash tax rate
A5: da_percent_revenue | B5: 0.04 | C5: auto_default | D5: D&A as % of revenue
A6: capex_percent_revenue | B6: 0.08 | C6: auto_default | D6: Capital expenditure as % of revenue
A7: nwc_percent_revenue | B7: 0.02 | C7: auto_default | D7: Change in working capital as % of revenue
A8: wacc | B8: 0.1 | C8: auto_default | D8: Weighted average cost of capital
A9: terminal_growth | B9: 0.03 | C9: auto_default | D9: Terminal growth rate
